graphknn.py
graphknn-1.0.0b1.dist-info/DESCRIPTION.rst
graphknn-1.0.0b1.dist-info/METADATA
graphknn-1.0.0b1.dist-info/RECORD
graphknn-1.0.0b1.dist-info/WHEEL
graphknn-1.0.0b1.dist-info/metadata.json
graphknn-1.0.0b1.dist-info/top_level.txt
graphknn-1.0.0b1.dist-info/zip-safe
