Metadata-Version: 2.0
Name: graphknn
Version: 1.0.0b1
Summary: For every vertex in a graph, this code efficiently finds its K nearest vertices from a particular subset of "special" vertices.
Home-page: https://github.com/mosco/graphknn
Author: Amit Moscovich
Author-email: moscovich@gmail.com
License: MIT
Keywords: graph knn dijkstra shortest path
Platform: UNKNOWN
Classifier: Development Status :: 4 - Beta
Classifier: Intended Audience :: Science/Research
Classifier: License :: OSI Approved :: MIT License
Classifier: Operating System :: OS Independent
Classifier: Programming Language :: Python :: 2
Classifier: Programming Language :: Python :: 3
Classifier: Topic :: Software Development :: Libraries :: Python Modules
Requires-Dist: HeapDict
Requires-Dist: SciPy
